training_data_debugger/__init__.py
training_data_debugger/debugger.py
training_data_debugger/types.py
training_data_debugger-0.1.0.dist-info/METADATA
training_data_debugger-0.1.0.dist-info/WHEEL
training_data_debugger-0.1.0.dist-info/licenses/LICENSE
training_data_debugger-0.1.0.dist-info/RECORD
