Metadata-Version: 2.4
Name: training-data-debugger
Version: 0.1.0
Summary: Find and fix issues in your ML training data - duplicates, label errors, outliers, and more
Project-URL: Homepage, https://github.com/pranaym/training-data-debugger
Project-URL: Documentation, https://github.com/pranaym/training-data-debugger#readme
Project-URL: Repository, https://github.com/pranaym/training-data-debugger
Project-URL: Issues, https://github.com/pranaym/training-data-debugger/issues
Project-URL: Changelog, https://github.com/pranaym/training-data-debugger/blob/main/CHANGELOG.md
Author-email: Pranay M <pranay@example.com>
License-Expression: MIT
License-File: LICENSE
Keywords: data-cleaning,data-quality,data-validation,debugging,duplicates,label-errors,machine-learning,mlops,outliers,training-data
Classifier: Development Status :: 4 - Beta
Classifier: Intended Audience :: Developers
Classifier: Intended Audience :: Science/Research
Classifier: License :: OSI Approved :: MIT License
Classifier: Operating System :: OS Independent
Classifier: Programming Language :: Python :: 3
Classifier: Programming Language :: Python :: 3.8
Classifier: Programming Language :: Python :: 3.9
Classifier: Programming Language :: Python :: 3.10
Classifier: Programming Language :: Python :: 3.11
Classifier: Programming Language :: Python :: 3.12
Classifier: Topic :: Scientific/Engineering :: Artificial Intelligence
Classifier: Topic :: Software Development :: Quality Assurance
Classifier: Typing :: Typed
Requires-Python: >=3.8
Provides-Extra: dev
Requires-Dist: black>=23.0.0; extra == 'dev'
Requires-Dist: mypy>=1.0.0; extra == 'dev'
Requires-Dist: pytest-cov>=4.0.0; extra == 'dev'
Requires-Dist: pytest>=7.0.0; extra == 'dev'
Requires-Dist: ruff>=0.1.0; extra == 'dev'
Provides-Extra: full
Requires-Dist: matplotlib>=3.5.0; extra == 'full'
Requires-Dist: numpy>=1.20.0; extra == 'full'
Requires-Dist: pandas>=1.3.0; extra == 'full'
Requires-Dist: scikit-learn>=1.0.0; extra == 'full'
Requires-Dist: seaborn>=0.11.0; extra == 'full'
Provides-Extra: ml
Requires-Dist: numpy>=1.20.0; extra == 'ml'
Requires-Dist: pandas>=1.3.0; extra == 'ml'
Requires-Dist: scikit-learn>=1.0.0; extra == 'ml'
Provides-Extra: viz
Requires-Dist: matplotlib>=3.5.0; extra == 'viz'
Requires-Dist: seaborn>=0.11.0; extra == 'viz'
